{"entityName":"Unnamed","coreSpriteID":"core1_light","coreShellSpriteID":"core3weapons_shell","shellHealth":[1000.0,250.0,500.0],"baseRegen":[60.0,0.0,30.0],"intendedType":0,"parts":[{"location":{"x":1.899999976158142,"y":1.0},"rotation":-15.0,"mirrored":false,"abilityID":20,"tier":3,"secondaryData":"","partID":"BigSide3","shiny":false,"playerGivenName":""},{"location":{"x":2.9000000953674318,"y":0.30000001192092898},"rotation":-105.0,"mirrored":false,"abilityID":9,"tier":2,"secondaryData":"","partID":"MediumWing2","shiny":false,"playerGivenName":""},{"location":{"x":-2.5999999046325685,"y":0.699999988079071},"rotation":105.0,"mirrored":false,"abilityID":19,"tier":3,"secondaryData":"","partID":"BigWing1","shiny":false,"playerGivenName":""},{"location":{"x":1.399999976158142,"y":-3.5},"rotation":120.0,"mirrored":false,"abilityID":9,"tier":2,"secondaryData":"","partID":"MediumWing2","shiny":false,"playerGivenName":""},{"location":{"x":1.2000004053115845,"y":-2.0999999046325685},"rotation":-45.0,"mirrored":false,"abilityID":20,"tier":3,"secondaryData":"","partID":"BigSide3","shiny":false,"playerGivenName":""},{"location":{"x":0.699999988079071,"y":0.699999988079071},"rotation":-15.0,"mirrored":false,"abilityID":21,"tier":0,"secondaryData":"","partID":"BigCenter1","shiny":false,"playerGivenName":""},{"location":{"x":1.100000023841858,"y":-0.7000000476837158},"rotation":-15.0,"mirrored":false,"abilityID":21,"tier":0,"secondaryData":"","partID":"BigCenter1","shiny":false,"playerGivenName":""},{"location":{"x":2.700000047683716,"y":-0.6000000238418579},"rotation":-90.0,"mirrored":false,"abilityID":19,"tier":3,"secondaryData":"","partID":"BigWing1","shiny":false,"playerGivenName":""},{"location":{"x":-0.800000011920929,"y":0.5},"rotation":15.0,"mirrored":false,"abilityID":8,"tier":2,"secondaryData":"","partID":"MediumSide4","shiny":false,"playerGivenName":""},{"location":{"x":-0.09999923408031464,"y":-1.0},"rotation":180.0,"mirrored":false,"abilityID":36,"tier":2,"secondaryData":"","partID":"MediumWing1","shiny":false,"playerGivenName":""},{"location":{"x":-5.800000190734863,"y":0.9999998211860657},"rotation":-30.0,"mirrored":false,"abilityID":36,"tier":2,"secondaryData":"","partID":"MediumWing1","shiny":false,"playerGivenName":""},{"location":{"x":0.10000000149011612,"y":-1.899999976158142},"rotation":0.0,"mirrored":false,"abilityID":8,"tier":2,"secondaryData":"","partID":"MediumCenter7","shiny":false,"playerGivenName":""},{"location":{"x":-6.199999809265137,"y":-0.10000000149011612},"rotation":15.0,"mirrored":false,"abilityID":26,"tier":2,"secondaryData":"","partID":"MediumSide2","shiny":false,"playerGivenName":""},{"location":{"x":-1.799999713897705,"y":-0.9000003337860107},"rotation":135.0,"mirrored":false,"abilityID":20,"tier":3,"secondaryData":"","partID":"BigSide3","shiny":false,"playerGivenName":""},{"location":{"x":-0.09999996423721314,"y":-3.700000047683716},"rotation":15.0,"mirrored":false,"abilityID":2,"tier":3,"secondaryData":"","partID":"BigCenter3","shiny":false,"playerGivenName":""},{"location":{"x":-1.100000023841858,"y":-2.4000000953674318},"rotation":165.0,"mirrored":true,"abilityID":19,"tier":3,"secondaryData":"","partID":"BigWing1","shiny":false,"playerGivenName":""},{"location":{"x":-5.099999904632568,"y":-0.5},"rotation":-105.0,"mirrored":false,"abilityID":2,"tier":3,"secondaryData":"","partID":"BigCenter3","shiny":false,"playerGivenName":""},{"location":{"x":-4.30000114440918,"y":0.5999995470046997},"rotation":-15.0,"mirrored":false,"abilityID":9,"tier":2,"secondaryData":"","partID":"MediumWing2","shiny":false,"playerGivenName":""},{"location":{"x":2.700000047683716,"y":2.200000047683716},"rotation":-45.0,"mirrored":false,"abilityID":2,"tier":3,"secondaryData":"","partID":"BigCenter3","shiny":false,"playerGivenName":""},{"location":{"x":3.799999952316284,"y":3.0},"rotation":-165.0,"mirrored":false,"abilityID":26,"tier":2,"secondaryData":"","partID":"MediumSide2","shiny":false,"playerGivenName":""},{"location":{"x":0.4000012278556824,"y":-5.099999904632568},"rotation":120.0,"mirrored":false,"abilityID":26,"tier":2,"secondaryData":"","partID":"MediumSide2","shiny":false,"playerGivenName":""},{"location":{"x":-3.799999952316284,"y":-1.0},"rotation":-30.0,"mirrored":false,"abilityID":10,"tier":0,"secondaryData":"{\"drone\":\"{\\\"entityName\\\":\\\"Gun Drone\\\",\\\"coreSpriteID\\\":\\\"drone_light\\\",\\\"coreShellSpriteID\\\":\\\"drone_shell\\\",\\\"shellHealth\\\":[1000.0,250.0,500.0],\\\"baseRegen\\\":[60.0,0.0,60.0],\\\"intendedType\\\":7,\\\"parts\\\":[{\\\"location\\\":{\\\"x\\\":0.20000001788139344,\\\"y\\\":-0.30000001192092898},\\\"rotation\\\":-15.0,\\\"mirrored\\\":false,\\\"abilityID\\\":17,\\\"tier\\\":1,\\\"secondaryData\\\":\\\"\\\",\\\"partID\\\":\\\"SmallSide4\\\",\\\"shiny\\\":false,\\\"playerGivenName\\\":\\\"\\\"},{\\\"location\\\":{\\\"x\\\":0.44856947660446169,\\\"y\\\":-0.10000000149011612},\\\"rotation\\\":30.0,\\\"mirrored\\\":false,\\\"abilityID\\\":6,\\\"tier\\\":1,\\\"secondaryData\\\":\\\"\\\",\\\"partID\\\":\\\"SmallSide4\\\",\\\"shiny\\\":false,\\\"playerGivenName\\\":\\\"\\\"},{\\\"location\\\":{\\\"x\\\":-0.2000000774860382,\\\"y\\\":0.19999998807907105},\\\"rotation\\\":-15.0,\\\"mirrored\\\":true,\\\"abilityID\\\":19,\\\"tier\\\":1,\\\"secondaryData\\\":\\\"\\\",\\\"partID\\\":\\\"SmallSide4\\\",\\\"shiny\\\":false,\\\"playerGivenName\\\":\\\"\\\"},{\\\"location\\\":{\\\"x\\\":-0.4485611021518707,\\\"y\\\":-0.10000000149011612},\\\"rotation\\\":15.0,\\\"mirrored\\\":true,\\\"abilityID\\\":6,\\\"tier\\\":1,\\\"secondaryData\\\":\\\"\\\",\\\"partID\\\":\\\"SmallSide4\\\",\\\"shiny\\\":false,\\\"playerGivenName\\\":\\\"\\\"}],\\\"dialogue\\\":{\\\"instanceID\\\":0},\\\"useCustomDroneType\\\":true,\\\"customDroneType\\\":4}\",\"energyCost\":150.0,\"delay\":3.0,\"cooldown\":15.0,\"type\":4}","partID":"BigSide5","shiny":false,"playerGivenName":""},{"location":{"x":-3.200000047683716,"y":-1.5},"rotation":15.0,"mirrored":false,"abilityID":10,"tier":0,"secondaryData":"{\"drone\":\"{\\\"entityName\\\":\\\"Strike Drone\\\",\\\"coreSpriteID\\\":\\\"drone_light\\\",\\\"coreShellSpriteID\\\":\\\"drone_shell\\\",\\\"shellHealth\\\":[1000.0,250.0,500.0],\\\"baseRegen\\\":[60.0,0.0,60.0],\\\"intendedType\\\":7,\\\"parts\\\":[{\\\"location\\\":{\\\"x\\\":0.2000000774860382,\\\"y\\\":-0.10000000149011612},\\\"rotation\\\":15.0,\\\"mirrored\\\":false,\\\"abilityID\\\":13,\\\"tier\\\":1,\\\"secondaryData\\\":\\\"\\\",\\\"partID\\\":\\\"SmallWing1\\\",\\\"shiny\\\":false,\\\"playerGivenName\\\":\\\"\\\"},{\\\"location\\\":{\\\"x\\\":-0.1999993771314621,\\\"y\\\":0.20000001788139344},\\\"rotation\\\":-15.0,\\\"mirrored\\\":true,\\\"abilityID\\\":5,\\\"tier\\\":1,\\\"secondaryData\\\":\\\"\\\",\\\"partID\\\":\\\"SmallWing1\\\",\\\"shiny\\\":false,\\\"playerGivenName\\\":\\\"\\\"},{\\\"location\\\":{\\\"x\\\":-0.5000000596046448,\\\"y\\\":0.09999997913837433},\\\"rotation\\\":-30.0,\\\"mirrored\\\":false,\\\"abilityID\\\":20,\\\"tier\\\":1,\\\"secondaryData\\\":\\\"\\\",\\\"partID\\\":\\\"SmallWing1\\\",\\\"shiny\\\":false,\\\"playerGivenName\\\":\\\"\\\"},{\\\"location\\\":{\\\"x\\\":0.5000001788139343,\\\"y\\\":-1.907348590179936e-8},\\\"rotation\\\":45.0,\\\"mirrored\\\":true,\\\"abilityID\\\":5,\\\"tier\\\":1,\\\"secondaryData\\\":\\\"\\\",\\\"partID\\\":\\\"SmallWing1\\\",\\\"shiny\\\":false,\\\"playerGivenName\\\":\\\"\\\"}],\\\"dialogue\\\":{\\\"m_FileID\\\":0,\\\"m_PathID\\\":0},\\\"useCustomDroneType\\\":true,\\\"customDroneType\\\":2}\",\"energyCost\":150.0,\"delay\":3.0,\"cooldown\":15.0,\"type\":2}","partID":"MediumSide2","shiny":false,"playerGivenName":""},{"location":{"x":-2.5999999046325685,"y":-0.6000000238418579},"rotation":-165.0,"mirrored":false,"abilityID":10,"tier":0,"secondaryData":"{\"drone\":\"{\\\"entityName\\\":\\\"Counter Drone\\\",\\\"coreSpriteID\\\":\\\"drone_light\\\",\\\"coreShellSpriteID\\\":\\\"drone_shell\\\",\\\"shellHealth\\\":[1000.0,250.0,500.0],\\\"baseRegen\\\":[60.0,0.0,60.0],\\\"intendedType\\\":7,\\\"parts\\\":[{\\\"location\\\":{\\\"x\\\":-0.30000001192092898,\\\"y\\\":3.814697180359872e-8},\\\"rotation\\\":-135.0,\\\"mirrored\\\":false,\\\"abilityID\\\":4,\\\"tier\\\":1,\\\"secondaryData\\\":\\\"\\\",\\\"partID\\\":\\\"SmallCenter5\\\",\\\"shiny\\\":false,\\\"playerGivenName\\\":\\\"\\\"},{\\\"location\\\":{\\\"x\\\":0.000003967285010730848,\\\"y\\\":-0.3499999940395355},\\\"rotation\\\":15.0,\\\"mirrored\\\":false,\\\"abilityID\\\":4,\\\"tier\\\":1,\\\"secondaryData\\\":\\\"\\\",\\\"partID\\\":\\\"SmallCenter5\\\",\\\"shiny\\\":false,\\\"playerGivenName\\\":\\\"\\\"},{\\\"location\\\":{\\\"x\\\":0.0,\\\"y\\\":-0.15000000596046449},\\\"rotation\\\":-15.0,\\\"mirrored\\\":false,\\\"abilityID\\\":17,\\\"tier\\\":1,\\\"secondaryData\\\":\\\"\\\",\\\"partID\\\":\\\"SmallCenter2\\\",\\\"shiny\\\":false,\\\"playerGivenName\\\":\\\"\\\"},{\\\"location\\\":{\\\"x\\\":0.40000224113464358,\\\"y\\\":1.9073486612342095e-7},\\\"rotation\\\":150.0,\\\"mirrored\\\":false,\\\"abilityID\\\":18,\\\"tier\\\":1,\\\"secondaryData\\\":\\\"\\\",\\\"partID\\\":\\\"SmallCenter2\\\",\\\"shiny\\\":false,\\\"playerGivenName\\\":\\\"\\\"}],\\\"dialogue\\\":{\\\"m_FileID\\\":0,\\\"m_PathID\\\":0},\\\"useCustomDroneType\\\":true,\\\"customDroneType\\\":5}\",\"energyCost\":150.0,\"delay\":3.0,\"cooldown\":15.0,\"type\":5}","partID":"MediumWing1","shiny":false,"playerGivenName":""},{"location":{"x":4.95910626341356e-7,"y":1.7000000476837159},"rotation":-30.0,"mirrored":false,"abilityID":37,"tier":3,"secondaryData":"","partID":"BigSide4","shiny":false,"playerGivenName":""}],"dialogue":{"instanceID":0},"useCustomDroneType":false,"customDroneType":0}