{"sectorjson":"{\"dimension\":0,\"sectorName\":\"BattleZone Epsilon\",\"bounds\":{\"x\":1100,\"y\":-590,\"w\":470,\"h\":270},\"type\":2,\"backgroundColor\":{\"r\":0.4000000059604645,\"g\":0.0,\"b\":0.0,\"a\":1.0},\"entities\":[{\"name\":\"Outpost\",\"ID\":\"108\",\"faction\":1,\"assetID\":\"outpost_blueprint\",\"blueprintJSON\":\"\",\"dialogueID\":\"\",\"vendingID\":\"\",\"pathID\":\"\",\"position\":{\"x\":1400.0,\"y\":-770.0},\"patrolPath\":{\"waypoints\":[]}},{\"name\":\"Outpost\",\"ID\":\"109\",\"faction\":1,\"assetID\":\"outpost_blueprint\",\"blueprintJSON\":\"\",\"dialogueID\":\"\",\"vendingID\":\"\",\"pathID\":\"\",\"position\":{\"x\":1270.0,\"y\":-680.0},\"patrolPath\":{\"waypoints\":[]}},{\"name\":\"Outpost\",\"ID\":\"110\",\"faction\":1,\"assetID\":\"outpost_blueprint\",\"blueprintJSON\":\"\",\"dialogueID\":\"\",\"vendingID\":\"\",\"pathID\":\"\",\"position\":{\"x\":1290.0,\"y\":-820.0},\"patrolPath\":{\"waypoints\":[]}},{\"name\":\"Outpost\",\"ID\":\"111\",\"faction\":1,\"assetID\":\"outpost_blueprint\",\"blueprintJSON\":\"\",\"dialogueID\":\"\",\"vendingID\":\"\",\"pathID\":\"\",\"position\":{\"x\":1380.0,\"y\":-820.0},\"patrolPath\":{\"waypoints\":[]}},{\"name\":\"Outpost\",\"ID\":\"112\",\"faction\":1,\"assetID\":\"outpost_blueprint\",\"blueprintJSON\":\"\",\"dialogueID\":\"\",\"vendingID\":\"\",\"pathID\":\"\",\"position\":{\"x\":1290.0,\"y\":-630.0},\"patrolPath\":{\"waypoints\":[]}},{\"name\":\"Outpost\",\"ID\":\"113\",\"faction\":1,\"assetID\":\"outpost_blueprint\",\"blueprintJSON\":\"\",\"dialogueID\":\"\",\"vendingID\":\"\",\"pathID\":\"\",\"position\":{\"x\":1380.0,\"y\":-630.0},\"patrolPath\":{\"waypoints\":[]}},{\"name\":\"Outpost\",\"ID\":\"114\",\"faction\":1,\"assetID\":\"outpost_blueprint\",\"blueprintJSON\":\"\",\"dialogueID\":\"\",\"vendingID\":\"\",\"pathID\":\"\",\"position\":{\"x\":1220.0,\"y\":-780.0},\"patrolPath\":{\"waypoints\":[]}},{\"name\":\"Outpost\",\"ID\":\"115\",\"faction\":1,\"assetID\":\"outpost_blueprint\",\"blueprintJSON\":\"\",\"dialogueID\":\"\",\"vendingID\":\"\",\"pathID\":\"\",\"position\":{\"x\":1450.0,\"y\":-670.0},\"patrolPath\":{\"waypoints\":[]}},{\"name\":\"Outpost\",\"ID\":\"116\",\"faction\":1,\"assetID\":\"outpost_blueprint\",\"blueprintJSON\":\"\",\"dialogueID\":\"\",\"vendingID\":\"\",\"pathID\":\"\",\"position\":{\"x\":1370.0,\"y\":-795.0},\"patrolPath\":{\"waypoints\":[]}},{\"name\":\"Outpost\",\"ID\":\"117\",\"faction\":1,\"assetID\":\"outpost_blueprint\",\"blueprintJSON\":\"\",\"dialogueID\":\"\",\"vendingID\":\"\",\"pathID\":\"\",\"position\":{\"x\":1300.0,\"y\":-655.0},\"patrolPath\":{\"waypoints\":[]}},{\"name\":\"Power Rock\",\"ID\":\"118\",\"faction\":0,\"assetID\":\"energy_rock\",\"blueprintJSON\":\"\",\"dialogueID\":\"\",\"vendingID\":\"\",\"pathID\":\"\",\"position\":{\"x\":1185.0,\"y\":-672.5},\"patrolPath\":{\"waypoints\":[]}},{\"name\":\"Power Rock\",\"ID\":\"119\",\"faction\":0,\"assetID\":\"energy_rock\",\"blueprintJSON\":\"\",\"dialogueID\":\"\",\"vendingID\":\"\",\"pathID\":\"\",\"position\":{\"x\":1485.0,\"y\":-777.5},\"patrolPath\":{\"waypoints\":[]}},{\"name\":\"Outpost\",\"ID\":\"120\",\"faction\":1,\"assetID\":\"outpost_blueprint\",\"blueprintJSON\":\"\",\"dialogueID\":\"\",\"vendingID\":\"\",\"pathID\":\"\",\"position\":{\"x\":1485.0,\"y\":-780.0},\"patrolPath\":{\"waypoints\":[]}},{\"name\":\"Outpost\",\"ID\":\"121\",\"faction\":1,\"assetID\":\"outpost_blueprint\",\"blueprintJSON\":\"\",\"dialogueID\":\"\",\"vendingID\":\"\",\"pathID\":\"\",\"position\":{\"x\":1185.0,\"y\":-670.0},\"patrolPath\":{\"waypoints\":[]}},{\"name\":\"Outpost\",\"ID\":\"122\",\"faction\":1,\"assetID\":\"outpost_blueprint\",\"blueprintJSON\":\"\",\"dialogueID\":\"\",\"vendingID\":\"\",\"pathID\":\"\",\"position\":{\"x\":1335.0,\"y\":-725.0},\"patrolPath\":{\"waypoints\":[]}},{\"name\":\"Power Rock\",\"ID\":\"123\",\"faction\":0,\"assetID\":\"energy_rock\",\"blueprintJSON\":\"\",\"dialogueID\":\"\",\"vendingID\":\"\",\"pathID\":\"\",\"position\":{\"x\":1250.0,\"y\":-712.5},\"patrolPath\":{\"waypoints\":[]}},{\"name\":\"Power Rock\",\"ID\":\"124\",\"faction\":0,\"assetID\":\"energy_rock\",\"blueprintJSON\":\"\",\"dialogueID\":\"\",\"vendingID\":\"\",\"pathID\":\"\",\"position\":{\"x\":1420.0,\"y\":-737.5},\"patrolPath\":{\"waypoints\":[]}},{\"name\":\"Outpost\",\"ID\":\"125\",\"faction\":1,\"assetID\":\"outpost_blueprint\",\"blueprintJSON\":\"\",\"dialogueID\":\"\",\"vendingID\":\"\",\"pathID\":\"\",\"position\":{\"x\":1420.0,\"y\":-740.0},\"patrolPath\":{\"waypoints\":[]}},{\"name\":\"Outpost\",\"ID\":\"126\",\"faction\":1,\"assetID\":\"outpost_blueprint\",\"blueprintJSON\":\"\",\"dialogueID\":\"\",\"vendingID\":\"\",\"pathID\":\"\",\"position\":{\"x\":1250.0,\"y\":-710.0},\"patrolPath\":{\"waypoints\":[]}},{\"name\":\"Power Rock\",\"ID\":\"127\",\"faction\":0,\"assetID\":\"energy_rock\",\"blueprintJSON\":\"\",\"dialogueID\":\"\",\"vendingID\":\"\",\"pathID\":\"\",\"position\":{\"x\":1297.5,\"y\":-792.5},\"patrolPath\":{\"waypoints\":[]}},{\"name\":\"Power Rock\",\"ID\":\"128\",\"faction\":0,\"assetID\":\"energy_rock\",\"blueprintJSON\":\"\",\"dialogueID\":\"\",\"vendingID\":\"\",\"pathID\":\"\",\"position\":{\"x\":1372.5,\"y\":-657.5},\"patrolPath\":{\"waypoints\":[]}},{\"name\":\"Outpost\",\"ID\":\"129\",\"faction\":1,\"assetID\":\"outpost_blueprint\",\"blueprintJSON\":\"\",\"dialogueID\":\"\",\"vendingID\":\"\",\"pathID\":\"\",\"position\":{\"x\":1370.0,\"y\":-655.0},\"patrolPath\":{\"waypoints\":[]}},{\"name\":\"Outpost\",\"ID\":\"130\",\"faction\":1,\"assetID\":\"outpost_blueprint\",\"blueprintJSON\":\"\",\"dialogueID\":\"\",\"vendingID\":\"\",\"pathID\":\"\",\"position\":{\"x\":1300.0,\"y\":-795.0},\"patrolPath\":{\"waypoints\":[]}},{\"name\":\"flag_scourgepythaspawnepsilon\",\"ID\":\"131\",\"faction\":0,\"assetID\":\"flag\",\"blueprintJSON\":\"\",\"dialogueID\":\"\",\"vendingID\":\"\",\"pathID\":\"\",\"position\":{\"x\":1505.0,\"y\":-732.5},\"patrolPath\":{\"waypoints\":[]}},{\"name\":\"flag_scourgedaayospawnepsilon\",\"ID\":\"132\",\"faction\":0,\"assetID\":\"flag\",\"blueprintJSON\":\"\",\"dialogueID\":\"\",\"vendingID\":\"\",\"pathID\":\"\",\"position\":{\"x\":1505.0,\"y\":-730.0},\"patrolPath\":{\"waypoints\":[]}},{\"name\":\"Siege Turret\",\"ID\":\"133\",\"faction\":1,\"assetID\":\"siege_turret\",\"blueprintJSON\":\"\",\"dialogueID\":\"\",\"vendingID\":\"\",\"pathID\":\"\",\"position\":{\"x\":1502.5,\"y\":-727.5},\"patrolPath\":{\"waypoints\":[]}},{\"name\":\"Siege Turret\",\"ID\":\"134\",\"faction\":1,\"assetID\":\"siege_turret\",\"blueprintJSON\":\"\",\"dialogueID\":\"\",\"vendingID\":\"\",\"pathID\":\"\",\"position\":{\"x\":1505.0,\"y\":-727.5},\"patrolPath\":{\"waypoints\":[]}},{\"name\":\"Siege Turret\",\"ID\":\"135\",\"faction\":1,\"assetID\":\"siege_turret\",\"blueprintJSON\":\"\",\"dialogueID\":\"\",\"vendingID\":\"\",\"pathID\":\"\",\"position\":{\"x\":1507.5,\"y\":-727.5},\"patrolPath\":{\"waypoints\":[]}},{\"name\":\"Siege Turret\",\"ID\":\"136\",\"faction\":1,\"assetID\":\"siege_turret\",\"blueprintJSON\":\"\",\"dialogueID\":\"\",\"vendingID\":\"\",\"pathID\":\"\",\"position\":{\"x\":1507.5,\"y\":-722.5},\"patrolPath\":{\"waypoints\":[]}},{\"name\":\"Siege Turret\",\"ID\":\"137\",\"faction\":1,\"assetID\":\"siege_turret\",\"blueprintJSON\":\"\",\"dialogueID\":\"\",\"vendingID\":\"\",\"pathID\":\"\",\"position\":{\"x\":1505.0,\"y\":-722.5},\"patrolPath\":{\"waypoints\":[]}},{\"name\":\"Siege Turret\",\"ID\":\"138\",\"faction\":1,\"assetID\":\"siege_turret\",\"blueprintJSON\":\"\",\"dialogueID\":\"\",\"vendingID\":\"\",\"pathID\":\"\",\"position\":{\"x\":1502.5,\"y\":-722.5},\"patrolPath\":{\"waypoints\":[]}},{\"name\":\"Defense Turret\",\"ID\":\"139\",\"faction\":1,\"assetID\":\"defense_turret\",\"blueprintJSON\":\"\",\"dialogueID\":\"\",\"vendingID\":\"\",\"pathID\":\"\",\"position\":{\"x\":1525.0,\"y\":-732.5},\"patrolPath\":{\"waypoints\":[]}},{\"name\":\"Defense Turret\",\"ID\":\"140\",\"faction\":1,\"assetID\":\"defense_turret\",\"blueprintJSON\":\"\",\"dialogueID\":\"\",\"vendingID\":\"\",\"pathID\":\"\",\"position\":{\"x\":1525.0,\"y\":-717.5},\"patrolPath\":{\"waypoints\":[]}},{\"name\":\"Defense Turret\",\"ID\":\"141\",\"faction\":1,\"assetID\":\"defense_turret\",\"blueprintJSON\":\"\",\"dialogueID\":\"\",\"vendingID\":\"\",\"pathID\":\"\",\"position\":{\"x\":1512.5,\"y\":-705.0},\"patrolPath\":{\"waypoints\":[]}},{\"name\":\"Defense Turret\",\"ID\":\"142\",\"faction\":1,\"assetID\":\"defense_turret\",\"blueprintJSON\":\"\",\"dialogueID\":\"\",\"vendingID\":\"\",\"pathID\":\"\",\"position\":{\"x\":1512.5,\"y\":-745.0},\"patrolPath\":{\"waypoints\":[]}},{\"name\":\"Defense Turret\",\"ID\":\"143\",\"faction\":1,\"assetID\":\"defense_turret\",\"blueprintJSON\":\"\",\"dialogueID\":\"\",\"vendingID\":\"\",\"pathID\":\"\",\"position\":{\"x\":1497.5,\"y\":-745.0},\"patrolPath\":{\"waypoints\":[]}},{\"name\":\"Defense Turret\",\"ID\":\"144\",\"faction\":1,\"assetID\":\"defense_turret\",\"blueprintJSON\":\"\",\"dialogueID\":\"\",\"vendingID\":\"\",\"pathID\":\"\",\"position\":{\"x\":1485.0,\"y\":-732.5},\"patrolPath\":{\"waypoints\":[]}},{\"name\":\"Defense Turret\",\"ID\":\"145\",\"faction\":1,\"assetID\":\"defense_turret\",\"blueprintJSON\":\"\",\"dialogueID\":\"\",\"vendingID\":\"\",\"pathID\":\"\",\"position\":{\"x\":1485.0,\"y\":-717.5},\"patrolPath\":{\"waypoints\":[]}},{\"name\":\"Defense Turret\",\"ID\":\"146\",\"faction\":1,\"assetID\":\"defense_turret\",\"blueprintJSON\":\"\",\"dialogueID\":\"\",\"vendingID\":\"\",\"pathID\":\"\",\"position\":{\"x\":1497.5,\"y\":-705.0},\"patrolPath\":{\"waypoints\":[]}},{\"name\":\"Defense Turret\",\"ID\":\"147\",\"faction\":1,\"assetID\":\"defense_turret\",\"blueprintJSON\":\"\",\"dialogueID\":\"\",\"vendingID\":\"\",\"pathID\":\"\",\"position\":{\"x\":1515.0,\"y\":-715.0},\"patrolPath\":{\"waypoints\":[]}},{\"name\":\"Defense Turret\",\"ID\":\"148\",\"faction\":1,\"assetID\":\"defense_turret\",\"blueprintJSON\":\"\",\"dialogueID\":\"\",\"vendingID\":\"\",\"pathID\":\"\",\"position\":{\"x\":1520.0,\"y\":-725.0},\"patrolPath\":{\"waypoints\":[]}},{\"name\":\"Defense Turret\",\"ID\":\"149\",\"faction\":1,\"assetID\":\"defense_turret\",\"blueprintJSON\":\"\",\"dialogueID\":\"\",\"vendingID\":\"\",\"pathID\":\"\",\"position\":{\"x\":1515.0,\"y\":-735.0},\"patrolPath\":{\"waypoints\":[]}},{\"name\":\"Defense Turret\",\"ID\":\"150\",\"faction\":1,\"assetID\":\"defense_turret\",\"blueprintJSON\":\"\",\"dialogueID\":\"\",\"vendingID\":\"\",\"pathID\":\"\",\"position\":{\"x\":1505.0,\"y\":-740.0},\"patrolPath\":{\"waypoints\":[]}},{\"name\":\"Defense Turret\",\"ID\":\"151\",\"faction\":1,\"assetID\":\"defense_turret\",\"blueprintJSON\":\"\",\"dialogueID\":\"\",\"vendingID\":\"\",\"pathID\":\"\",\"position\":{\"x\":1495.0,\"y\":-735.0},\"patrolPath\":{\"waypoints\":[]}},{\"name\":\"Defense Turret\",\"ID\":\"152\",\"faction\":1,\"assetID\":\"defense_turret\",\"blueprintJSON\":\"\",\"dialogueID\":\"\",\"vendingID\":\"\",\"pathID\":\"\",\"position\":{\"x\":1490.0,\"y\":-725.0},\"patrolPath\":{\"waypoints\":[]}},{\"name\":\"Defense Turret\",\"ID\":\"153\",\"faction\":1,\"assetID\":\"defense_turret\",\"blueprintJSON\":\"\",\"dialogueID\":\"\",\"vendingID\":\"\",\"pathID\":\"\",\"position\":{\"x\":1495.0,\"y\":-715.0},\"patrolPath\":{\"waypoints\":[]}},{\"name\":\"Defense Turret\",\"ID\":\"154\",\"faction\":1,\"assetID\":\"defense_turret\",\"blueprintJSON\":\"\",\"dialogueID\":\"\",\"vendingID\":\"\",\"pathID\":\"\",\"position\":{\"x\":1505.0,\"y\":-710.0},\"patrolPath\":{\"waypoints\":[]}},{\"name\":\"Power Rock\",\"ID\":\"155\",\"faction\":0,\"assetID\":\"energy_rock\",\"blueprintJSON\":\"\",\"dialogueID\":\"\",\"vendingID\":\"\",\"pathID\":\"\",\"position\":{\"x\":1135.0,\"y\":-647.5},\"patrolPath\":{\"waypoints\":[]}},{\"name\":\"Power Rock\",\"ID\":\"156\",\"faction\":0,\"assetID\":\"energy_rock\",\"blueprintJSON\":\"\",\"dialogueID\":\"\",\"vendingID\":\"\",\"pathID\":\"\",\"position\":{\"x\":1135.0,\"y\":-802.5},\"patrolPath\":{\"waypoints\":[]}},{\"name\":\"Power Rock\",\"ID\":\"157\",\"faction\":0,\"assetID\":\"energy_rock\",\"blueprintJSON\":\"\",\"dialogueID\":\"\",\"vendingID\":\"\",\"pathID\":\"\",\"position\":{\"x\":1422.5,\"y\":-615.0},\"patrolPath\":{\"waypoints\":[]}},{\"name\":\"Power Rock\",\"ID\":\"158\",\"faction\":0,\"assetID\":\"energy_rock\",\"blueprintJSON\":\"\",\"dialogueID\":\"\",\"vendingID\":\"\",\"pathID\":\"\",\"position\":{\"x\":1422.5,\"y\":-835.0},\"patrolPath\":{\"waypoints\":[]}},{\"name\":\"Power Rock\",\"ID\":\"159\",\"faction\":0,\"assetID\":\"energy_rock\",\"blueprintJSON\":\"\",\"dialogueID\":\"\",\"vendingID\":\"\",\"pathID\":\"\",\"position\":{\"x\":1332.5,\"y\":-845.0},\"patrolPath\":{\"waypoints\":[]}},{\"name\":\"Power Rock\",\"ID\":\"160\",\"faction\":0,\"assetID\":\"energy_rock\",\"blueprintJSON\":\"\",\"dialogueID\":\"\",\"vendingID\":\"\",\"pathID\":\"\",\"position\":{\"x\":1337.5,\"y\":-605.0},\"patrolPath\":{\"waypoints\":[]}},{\"name\":\"Power Rock\",\"ID\":\"161\",\"faction\":0,\"assetID\":\"energy_rock\",\"blueprintJSON\":\"\",\"dialogueID\":\"\",\"vendingID\":\"\",\"pathID\":\"\",\"position\":{\"x\":1247.5,\"y\":-615.0},\"patrolPath\":{\"waypoints\":[]}},{\"name\":\"Power Rock\",\"ID\":\"162\",\"faction\":0,\"assetID\":\"energy_rock\",\"blueprintJSON\":\"\",\"dialogueID\":\"\",\"vendingID\":\"\",\"pathID\":\"\",\"position\":{\"x\":1247.5,\"y\":-835.0},\"patrolPath\":{\"waypoints\":[]}},{\"name\":\"Outpost\",\"ID\":\"163\",\"faction\":1,\"assetID\":\"outpost_blueprint\",\"blueprintJSON\":\"\",\"dialogueID\":\"\",\"vendingID\":\"\",\"pathID\":\"\",\"position\":{\"x\":1425.0,\"y\":-615.0},\"patrolPath\":{\"waypoints\":[]}},{\"name\":\"Outpost\",\"ID\":\"164\",\"faction\":1,\"assetID\":\"outpost_blueprint\",\"blueprintJSON\":\"\",\"dialogueID\":\"\",\"vendingID\":\"\",\"pathID\":\"\",\"position\":{\"x\":1425.0,\"y\":-835.0},\"patrolPath\":{\"waypoints\":[]}},{\"name\":\"Outpost\",\"ID\":\"165\",\"faction\":1,\"assetID\":\"outpost_blueprint\",\"blueprintJSON\":\"\",\"dialogueID\":\"\",\"vendingID\":\"\",\"pathID\":\"\",\"position\":{\"x\":1245.0,\"y\":-835.0},\"patrolPath\":{\"waypoints\":[]}},{\"name\":\"Outpost\",\"ID\":\"166\",\"faction\":1,\"assetID\":\"outpost_blueprint\",\"blueprintJSON\":\"\",\"dialogueID\":\"\",\"vendingID\":\"\",\"pathID\":\"\",\"position\":{\"x\":1245.0,\"y\":-615.0},\"patrolPath\":{\"waypoints\":[]}},{\"name\":\"Outpost\",\"ID\":\"167\",\"faction\":1,\"assetID\":\"outpost_blueprint\",\"blueprintJSON\":\"\",\"dialogueID\":\"\",\"vendingID\":\"\",\"pathID\":\"\",\"position\":{\"x\":1335.0,\"y\":-605.0},\"patrolPath\":{\"waypoints\":[]}},{\"name\":\"Outpost\",\"ID\":\"168\",\"faction\":1,\"assetID\":\"outpost_blueprint\",\"blueprintJSON\":\"\",\"dialogueID\":\"\",\"vendingID\":\"\",\"pathID\":\"\",\"position\":{\"x\":1335.0,\"y\":-845.0},\"patrolPath\":{\"waypoints\":[]}},{\"name\":\"Outpost\",\"ID\":\"169\",\"faction\":1,\"assetID\":\"outpost_blueprint\",\"blueprintJSON\":\"\",\"dialogueID\":\"\",\"vendingID\":\"\",\"pathID\":\"\",\"position\":{\"x\":1535.0,\"y\":-805.0},\"patrolPath\":{\"waypoints\":[]}},{\"name\":\"Outpost\",\"ID\":\"170\",\"faction\":1,\"assetID\":\"outpost_blueprint\",\"blueprintJSON\":\"\",\"dialogueID\":\"\",\"vendingID\":\"\",\"pathID\":\"\",\"position\":{\"x\":1535.0,\"y\":-645.0},\"patrolPath\":{\"waypoints\":[]}},{\"name\":\"Power Rock\",\"ID\":\"171\",\"faction\":0,\"assetID\":\"energy_rock\",\"blueprintJSON\":\"\",\"dialogueID\":\"\",\"vendingID\":\"\",\"pathID\":\"\",\"position\":{\"x\":1535.0,\"y\":-647.5},\"patrolPath\":{\"waypoints\":[]}},{\"name\":\"Outpost\",\"ID\":\"172\",\"faction\":0,\"assetID\":\"outpost_blueprint\",\"blueprintJSON\":\"\",\"dialogueID\":\"\",\"vendingID\":\"\",\"pathID\":\"\",\"position\":{\"x\":1135.0,\"y\":-805.0},\"patrolPath\":{\"waypoints\":[]}},{\"name\":\"Outpost\",\"ID\":\"173\",\"faction\":0,\"assetID\":\"outpost_blueprint\",\"blueprintJSON\":\"\",\"dialogueID\":\"\",\"vendingID\":\"\",\"pathID\":\"\",\"position\":{\"x\":1135.0,\"y\":-645.0},\"patrolPath\":{\"waypoints\":[]}},{\"name\":\"Air Carrier\",\"ID\":\"174\",\"faction\":0,\"assetID\":\"carrier_blueprint\",\"blueprintJSON\":\"\",\"dialogueID\":\"\",\"vendingID\":\"\",\"pathID\":\"\",\"position\":{\"x\":1165.0,\"y\":-725.0},\"patrolPath\":{\"waypoints\":[]}},{\"name\":\"Air Carrier\",\"ID\":\"175\",\"faction\":1,\"assetID\":\"carrier_blueprint\",\"blueprintJSON\":\"\",\"dialogueID\":\"\",\"vendingID\":\"\",\"pathID\":\"\",\"position\":{\"x\":1505.0,\"y\":-725.0},\"patrolPath\":{\"waypoints\":[]}},{\"name\":\"Power Rock\",\"ID\":\"176\",\"faction\":0,\"assetID\":\"energy_rock\",\"blueprintJSON\":\"\",\"dialogueID\":\"\",\"vendingID\":\"\",\"pathID\":\"\",\"position\":{\"x\":1535.0,\"y\":-802.5},\"patrolPath\":{\"waypoints\":[]}},{\"name\":\"Map Background 1\",\"ID\":\"177\",\"faction\":0,\"assetID\":\"mapbg1\",\"blueprintJSON\":\"\",\"dialogueID\":\"\",\"vendingID\":\"\",\"pathID\":\"\",\"position\":{\"x\":1335.0,\"y\":-725.0},\"patrolPath\":{\"waypoints\":[]}}],\"platformData\":[],\"platform\":{\"instanceID\":0},\"targets\":[\"174\",\"175\"],\"hasMusic\":true,\"musicID\":\"music_fast\",\"partDropsDisabled\":false,\"backgroundSpawns\":[],\"waveSetPath\":\"\",\"rectangleEffectSkin\":0,\"backgroundTileSkin\":0,\"shardCountSet\":[0,0,0]}","platformjson":""}