{"sectorjson":"{\"dimension\":0,\"sectorName\":\"Sector 2040-180\",\"bounds\":{\"x\":1910,\"y\":150,\"w\":90,\"h\":90},\"type\":0,\"backgroundColor\":{\"r\":0.4000000059604645,\"g\":0.0,\"b\":0.0,\"a\":1.0},\"entities\":[{\"name\":\"HideoutAmbushFlag3\",\"ID\":\"HideoutAmbushFlag3\",\"faction\":0,\"assetID\":\"flag\",\"blueprintJSON\":\"\",\"dialogueID\":\"\",\"vendingID\":\"\",\"pathID\":\"\",\"position\":{\"x\":1997.5,\"y\":62.5},\"patrolPath\":{\"waypoints\":[]}},{\"name\":\"HideoutAmbushFlag1\",\"ID\":\"HideoutAmbushFlag1\",\"faction\":0,\"assetID\":\"flag\",\"blueprintJSON\":\"\",\"dialogueID\":\"\",\"vendingID\":\"\",\"pathID\":\"\",\"position\":{\"x\":1912.5,\"y\":62.5},\"patrolPath\":{\"waypoints\":[]}},{\"name\":\"HideoutAmbushFlag2\",\"ID\":\"HideoutAmbushFlag2\",\"faction\":0,\"assetID\":\"flag\",\"blueprintJSON\":\"\",\"dialogueID\":\"\",\"vendingID\":\"\",\"pathID\":\"\",\"position\":{\"x\":1955.0,\"y\":62.5},\"patrolPath\":{\"waypoints\":[]}},{\"name\":\"Power Rock\",\"ID\":\"1672\",\"faction\":1,\"assetID\":\"energy_rock\",\"blueprintJSON\":\"\",\"dialogueID\":\"\",\"vendingID\":\"\",\"pathID\":\"\",\"position\":{\"x\":1930.0,\"y\":107.5},\"patrolPath\":{\"waypoints\":[]}},{\"name\":\"Power Rock\",\"ID\":\"1673\",\"faction\":1,\"assetID\":\"energy_rock\",\"blueprintJSON\":\"\",\"dialogueID\":\"\",\"vendingID\":\"\",\"pathID\":\"\",\"position\":{\"x\":1980.0,\"y\":107.5},\"patrolPath\":{\"waypoints\":[]}},{\"name\":\"Outpost\",\"ID\":\"1674\",\"faction\":1,\"assetID\":\"outpost_blueprint\",\"blueprintJSON\":\"\",\"dialogueID\":\"\",\"vendingID\":\"\",\"pathID\":\"\",\"position\":{\"x\":1977.5,\"y\":105.0},\"patrolPath\":{\"waypoints\":[]}},{\"name\":\"Outpost\",\"ID\":\"1675\",\"faction\":1,\"assetID\":\"outpost_blueprint\",\"blueprintJSON\":\"\",\"dialogueID\":\"\",\"vendingID\":\"\",\"pathID\":\"\",\"position\":{\"x\":1932.5,\"y\":105.0},\"patrolPath\":{\"waypoints\":[]}},{\"name\":\"Missile Tank\",\"ID\":\"1676\",\"faction\":1,\"assetID\":\"missile_tank\",\"blueprintJSON\":\"\",\"dialogueID\":\"\",\"vendingID\":\"\",\"pathID\":\"\",\"position\":{\"x\":1985.0,\"y\":135.0},\"patrolPath\":{\"waypoints\":[]}},{\"name\":\"Missile Tank\",\"ID\":\"1677\",\"faction\":1,\"assetID\":\"missile_tank\",\"blueprintJSON\":\"\",\"dialogueID\":\"\",\"vendingID\":\"\",\"pathID\":\"\",\"position\":{\"x\":1925.0,\"y\":135.0},\"patrolPath\":{\"waypoints\":[]}},{\"name\":\"Missile Tank\",\"ID\":\"1678\",\"faction\":1,\"assetID\":\"missile_tank\",\"blueprintJSON\":\"\",\"dialogueID\":\"\",\"vendingID\":\"\",\"pathID\":\"\",\"position\":{\"x\":1925.0,\"y\":75.0},\"patrolPath\":{\"waypoints\":[]}},{\"name\":\"Missile Tank\",\"ID\":\"1679\",\"faction\":1,\"assetID\":\"missile_tank\",\"blueprintJSON\":\"\",\"dialogueID\":\"\",\"vendingID\":\"\",\"pathID\":\"\",\"position\":{\"x\":1985.0,\"y\":75.0},\"patrolPath\":{\"waypoints\":[]}},{\"name\":\"Defense Turret\",\"ID\":\"1680\",\"faction\":1,\"assetID\":\"defense_turret\",\"blueprintJSON\":\"\",\"dialogueID\":\"\",\"vendingID\":\"\",\"pathID\":\"\",\"position\":{\"x\":1932.5,\"y\":127.5},\"patrolPath\":{\"waypoints\":[]}},{\"name\":\"Defense Turret\",\"ID\":\"1681\",\"faction\":1,\"assetID\":\"defense_turret\",\"blueprintJSON\":\"\",\"dialogueID\":\"\",\"vendingID\":\"\",\"pathID\":\"\",\"position\":{\"x\":1977.5,\"y\":127.5},\"patrolPath\":{\"waypoints\":[]}},{\"name\":\"Defense Turret\",\"ID\":\"1682\",\"faction\":1,\"assetID\":\"defense_turret\",\"blueprintJSON\":\"\",\"dialogueID\":\"\",\"vendingID\":\"\",\"pathID\":\"\",\"position\":{\"x\":1977.5,\"y\":82.5},\"patrolPath\":{\"waypoints\":[]}},{\"name\":\"Defense Turret\",\"ID\":\"1683\",\"faction\":1,\"assetID\":\"defense_turret\",\"blueprintJSON\":\"\",\"dialogueID\":\"\",\"vendingID\":\"\",\"pathID\":\"\",\"position\":{\"x\":1932.5,\"y\":82.5},\"patrolPath\":{\"waypoints\":[]}},{\"name\":\"Yard\",\"ID\":\"HideoutYard1\",\"faction\":1,\"assetID\":\"yard_blueprint\",\"blueprintJSON\":\"\",\"dialogueID\":\"\",\"vendingID\":\"\",\"pathID\":\"\",\"position\":{\"x\":1967.5,\"y\":122.5},\"patrolPath\":{\"waypoints\":[]}},{\"name\":\"Trader\",\"ID\":\"HideoutTrader1\",\"faction\":1,\"assetID\":\"trader_blueprint\",\"blueprintJSON\":\"{\\\"parts\\\":[]}\",\"dialogueID\":\"\",\"vendingID\":\"\",\"pathID\":\"\",\"position\":{\"x\":1942.5,\"y\":122.5},\"patrolPath\":{\"waypoints\":[]}},{\"name\":\"Mission Control\",\"ID\":\"HideoutControl1\",\"faction\":1,\"assetID\":\"missioncontrol_blueprint\",\"blueprintJSON\":\"\",\"dialogueID\":\"\",\"vendingID\":\"\",\"pathID\":\"\",\"position\":{\"x\":1955.0,\"y\":132.5},\"patrolPath\":{\"waypoints\":[]}},{\"name\":\"Map Background 4\",\"ID\":\"1684\",\"faction\":1,\"assetID\":\"mapbg4\",\"blueprintJSON\":\"\",\"dialogueID\":\"\",\"vendingID\":\"\",\"pathID\":\"\",\"position\":{\"x\":1955.0,\"y\":105.0},\"patrolPath\":{\"waypoints\":[]}}],\"platformData\":[\"+020101010300\",\"+020107010300\",\"+020107070300\",\"+020101070300\"],\"platform\":{\"instanceID\":0},\"targets\":[],\"hasMusic\":true,\"musicID\":\"music_overworld_enemy_short\",\"partDropsDisabled\":false,\"backgroundSpawns\":[],\"waveSetPath\":\"\",\"rectangleEffectSkin\":1,\"backgroundTileSkin\":1,\"shardCountSet\":[0,0,0]}","platformjson":""}