{"sectorjson":"{\"dimension\":0,\"sectorName\":\"Danger Zone 2750-6910\",\"bounds\":{\"x\":2630,\"y\":-6580,\"w\":190,\"h\":240},\"type\":3,\"backgroundColor\":{\"r\":0.6499999761581421,\"g\":0.0,\"b\":0.0,\"a\":1.0},\"entities\":[{\"name\":\"Map Background 4\",\"ID\":\"3929\",\"faction\":1,\"assetID\":\"mapbg4\",\"blueprintJSON\":\"\",\"dialogueID\":\"\",\"vendingID\":\"\",\"pathID\":\"\",\"position\":{\"x\":2725.0,\"y\":-6700.0},\"patrolPath\":{\"waypoints\":[]}}],\"platformData\":[],\"platform\":{\"instanceID\":0},\"targets\":[],\"hasMusic\":true,\"musicID\":\"music_overworld_3\",\"partDropsDisabled\":false,\"backgroundSpawns\":[{\"entity\":{\"name\":\"ShellCore\",\"ID\":\"\",\"faction\":1,\"assetID\":\"shellcore_blueprint\",\"blueprintJSON\":\"Mephistopheles\",\"dialogueID\":\"\",\"vendingID\":\"\",\"pathID\":\"\",\"position\":{\"x\":0.0,\"y\":0.0},\"patrolPath\":{\"waypoints\":[]}},\"timePerSpawn\":8,\"radius\":15.0}],\"waveSetPath\":\"\",\"rectangleEffectSkin\":2,\"backgroundTileSkin\":1,\"shardCountSet\":[0,0,0]}","platformjson":""}