{"sectorjson":"{\"dimension\":0,\"sectorName\":\"Sector 800-5650\",\"bounds\":{\"x\":680,\"y\":-5400,\"w\":160,\"h\":210},\"type\":5,\"backgroundColor\":{\"r\":0.15000000596046449,\"g\":0.15000000596046449,\"b\":0.15000000596046449,\"a\":1.0},\"entities\":[{\"name\":\"ShellCore\",\"ID\":\"6172\",\"faction\":2,\"assetID\":\"shellcore_blueprint\",\"blueprintJSON\":\"Defected Renegade\",\"dialogueID\":\"\",\"vendingID\":\"\",\"pathID\":\"\",\"position\":{\"x\":752.5,\"y\":-5505.0},\"patrolPath\":{\"waypoints\":[{\"position\":{\"x\":752.5432739257813,\"y\":-5505.1455078125},\"ID\":0,\"children\":[2]},{\"position\":{\"x\":725.8720703125,\"y\":-5496.26220703125},\"ID\":2,\"children\":[3]},{\"position\":{\"x\":721.7920532226563,\"y\":-5459.32373046875},\"ID\":3,\"children\":[4]},{\"position\":{\"x\":752.0816040039063,\"y\":-5437.40283203125},\"ID\":4,\"children\":[8]},{\"position\":{\"x\":789.0368041992188,\"y\":-5452.9169921875},\"ID\":8,\"children\":[9]},{\"position\":{\"x\":793.5449829101563,\"y\":-5488.982421875},\"ID\":9,\"children\":[]}]}},{\"name\":\"ShellCore\",\"ID\":\"6173\",\"faction\":2,\"assetID\":\"shellcore_blueprint\",\"blueprintJSON\":\"Defected Breaker\",\"dialogueID\":\"\",\"vendingID\":\"\",\"pathID\":\"\",\"position\":{\"x\":802.5,\"y\":-5505.0},\"patrolPath\":{\"waypoints\":[{\"position\":{\"x\":802.5578002929688,\"y\":-5505.26806640625},\"ID\":0,\"children\":[11]},{\"position\":{\"x\":831.9043579101563,\"y\":-5481.2099609375},\"ID\":11,\"children\":[12]},{\"position\":{\"x\":801.9033203125,\"y\":-5451.7998046875},\"ID\":12,\"children\":[13]},{\"position\":{\"x\":771.0054321289063,\"y\":-5477.80029296875},\"ID\":13,\"children\":[]}]}},{\"name\":\"ShellCore\",\"ID\":\"6174\",\"faction\":2,\"assetID\":\"shellcore_blueprint\",\"blueprintJSON\":\"Defected Breaker\",\"dialogueID\":\"\",\"vendingID\":\"\",\"pathID\":\"\",\"position\":{\"x\":775.0,\"y\":-5452.5},\"patrolPath\":{\"waypoints\":[{\"position\":{\"x\":774.9961547851563,\"y\":-5452.41650390625},\"ID\":0,\"children\":[22]},{\"position\":{\"x\":735.0004272460938,\"y\":-5487.3271484375},\"ID\":22,\"children\":[23]},{\"position\":{\"x\":781.2335205078125,\"y\":-5534.9912109375},\"ID\":23,\"children\":[24]},{\"position\":{\"x\":828.4838256835938,\"y\":-5492.1240234375},\"ID\":24,\"children\":[]}]}},{\"name\":\"ShellCore\",\"ID\":\"6175\",\"faction\":2,\"assetID\":\"shellcore_blueprint\",\"blueprintJSON\":\"Defected Breaker\",\"dialogueID\":\"\",\"vendingID\":\"\",\"pathID\":\"\",\"position\":{\"x\":797.5,\"y\":-5565.0},\"patrolPath\":{\"waypoints\":[{\"position\":{\"x\":797.4962158203125,\"y\":-5565.0966796875},\"ID\":0,\"children\":[8]},{\"position\":{\"x\":762.9885864257813,\"y\":-5526.09033203125},\"ID\":8,\"children\":[9]},{\"position\":{\"x\":721.42919921875,\"y\":-5561.53271484375},\"ID\":9,\"children\":[10]},{\"position\":{\"x\":757.3540649414063,\"y\":-5597.556640625},\"ID\":10,\"children\":[]}]}},{\"name\":\"ShellCore\",\"ID\":\"6176\",\"faction\":2,\"assetID\":\"shellcore_blueprint\",\"blueprintJSON\":\"Defected Awful Scout\",\"dialogueID\":\"\",\"vendingID\":\"\",\"pathID\":\"\",\"position\":{\"x\":712.5,\"y\":-5510.0},\"patrolPath\":{\"waypoints\":[{\"position\":{\"x\":712.5565795898438,\"y\":-5510.20654296875},\"ID\":0,\"children\":[31]},{\"position\":{\"x\":708.7721557617188,\"y\":-5532.15966796875},\"ID\":31,\"children\":[32]},{\"position\":{\"x\":729.1614379882813,\"y\":-5553.7705078125},\"ID\":32,\"children\":[33]},{\"position\":{\"x\":761.57421875,\"y\":-5529.8642578125},\"ID\":33,\"children\":[34]},{\"position\":{\"x\":807.01123046875,\"y\":-5552.341796875},\"ID\":34,\"children\":[35]},{\"position\":{\"x\":822.8321533203125,\"y\":-5514.3662109375},\"ID\":35,\"children\":[36]},{\"position\":{\"x\":786.6150512695313,\"y\":-5478.41455078125},\"ID\":36,\"children\":[37]},{\"position\":{\"x\":764.2885131835938,\"y\":-5495.28662109375},\"ID\":37,\"children\":[38]},{\"position\":{\"x\":727.7210693359375,\"y\":-5482.646484375},\"ID\":38,\"children\":[]}]}},{\"name\":\"ShellCore\",\"ID\":\"6177\",\"faction\":2,\"assetID\":\"shellcore_blueprint\",\"blueprintJSON\":\"Defected Ioniser\",\"dialogueID\":\"\",\"vendingID\":\"\",\"pathID\":\"\",\"position\":{\"x\":792.5,\"y\":-5480.0},\"patrolPath\":{\"waypoints\":[{\"position\":{\"x\":792.6078491210938,\"y\":-5479.93505859375},\"ID\":0,\"children\":[14]},{\"position\":{\"x\":772.4498901367188,\"y\":-5510.7958984375},\"ID\":14,\"children\":[15]},{\"position\":{\"x\":796.006103515625,\"y\":-5520.69091796875},\"ID\":15,\"children\":[16]},{\"position\":{\"x\":797.4143676757813,\"y\":-5548.03857421875},\"ID\":16,\"children\":[]}]}},{\"name\":\"ShellCore\",\"ID\":\"6178\",\"faction\":2,\"assetID\":\"shellcore_blueprint\",\"blueprintJSON\":\"Defected Awful Scout\",\"dialogueID\":\"\",\"vendingID\":\"\",\"pathID\":\"\",\"position\":{\"x\":790.0,\"y\":-5440.0},\"patrolPath\":{\"waypoints\":[{\"position\":{\"x\":789.9652099609375,\"y\":-5440.02197265625},\"ID\":0,\"children\":[28]},{\"position\":{\"x\":757.9859619140625,\"y\":-5460.6943359375},\"ID\":28,\"children\":[29]},{\"position\":{\"x\":783.9529418945313,\"y\":-5481.81591796875},\"ID\":29,\"children\":[30]},{\"position\":{\"x\":773.4074096679688,\"y\":-5516.18408203125},\"ID\":30,\"children\":[]}]}},{\"name\":\"ShellCore\",\"ID\":\"6179\",\"faction\":2,\"assetID\":\"shellcore_blueprint\",\"blueprintJSON\":\"Defected Awful Scout\",\"dialogueID\":\"\",\"vendingID\":\"\",\"pathID\":\"\",\"position\":{\"x\":740.0,\"y\":-5467.5},\"patrolPath\":{\"waypoints\":[{\"position\":{\"x\":740.0435180664063,\"y\":-5467.35107421875},\"ID\":0,\"children\":[17]},{\"position\":{\"x\":722.3863525390625,\"y\":-5482.6171875},\"ID\":17,\"children\":[20]},{\"position\":{\"x\":716.9318237304688,\"y\":-5453.25927734375},\"ID\":20,\"children\":[21]},{\"position\":{\"x\":690.0369262695313,\"y\":-5439.1904296875},\"ID\":21,\"children\":[]}]}},{\"name\":\"ShellCore\",\"ID\":\"6180\",\"faction\":2,\"assetID\":\"shellcore_blueprint\",\"blueprintJSON\":\"Defected Ioniser\",\"dialogueID\":\"\",\"vendingID\":\"\",\"pathID\":\"\",\"position\":{\"x\":780.0,\"y\":-5527.5},\"patrolPath\":{\"waypoints\":[{\"position\":{\"x\":780.0128784179688,\"y\":-5527.39794921875},\"ID\":0,\"children\":[1]},{\"position\":{\"x\":761.8831176757813,\"y\":-5501.583984375},\"ID\":1,\"children\":[2]},{\"position\":{\"x\":729.8486328125,\"y\":-5535.333984375},\"ID\":2,\"children\":[4]},{\"position\":{\"x\":705.3236694335938,\"y\":-5537.0517578125},\"ID\":4,\"children\":[]}]}},{\"name\":\"ShellCore\",\"ID\":\"6181\",\"faction\":2,\"assetID\":\"shellcore_blueprint\",\"blueprintJSON\":\"Defected Ioniser\",\"dialogueID\":\"\",\"vendingID\":\"\",\"pathID\":\"\",\"position\":{\"x\":727.5,\"y\":-5560.0},\"patrolPath\":{\"waypoints\":[{\"position\":{\"x\":727.4246215820313,\"y\":-5559.953125},\"ID\":0,\"children\":[5]},{\"position\":{\"x\":745.1985473632813,\"y\":-5570.27197265625},\"ID\":5,\"children\":[6]},{\"position\":{\"x\":773.125,\"y\":-5547.2568359375},\"ID\":6,\"children\":[7]},{\"position\":{\"x\":815.8869018554688,\"y\":-5547.2568359375},\"ID\":7,\"children\":[]}]}},{\"name\":\"Map Background 3\",\"ID\":\"6182\",\"faction\":2,\"assetID\":\"mapbg3\",\"blueprintJSON\":\"\",\"dialogueID\":\"\",\"vendingID\":\"\",\"pathID\":\"\",\"position\":{\"x\":760.0,\"y\":-5505.0},\"patrolPath\":{\"waypoints\":[]}}],\"platformData\":[],\"platform\":{\"instanceID\":0},\"targets\":[\"6172\",\"6173\",\"6174\",\"6175\",\"6176\",\"6177\",\"6178\",\"6179\",\"6180\",\"6181\"],\"hasMusic\":true,\"musicID\":\"music_overworld_3\",\"partDropsDisabled\":false,\"backgroundSpawns\":[{\"entity\":{\"name\":\"ShellCore\",\"ID\":\"\",\"faction\":2,\"assetID\":\"shellcore_blueprint\",\"blueprintJSON\":\"Defected DroneHeavy\",\"dialogueID\":\"\",\"vendingID\":\"\",\"pathID\":\"\",\"position\":{\"x\":0.0,\"y\":0.0},\"patrolPath\":{\"waypoints\":[]}},\"timePerSpawn\":8,\"radius\":15.0}],\"waveSetPath\":\"\",\"gasVortices\":0,\"rectangleEffectSkin\":2,\"backgroundTileSkin\":1,\"shardCountSet\":[6,0,0]}","platformjson":""}